epubscraper.py
setup.py
epubscraper.egg-info/PKG-INFO
epubscraper.egg-info/SOURCES.txt
epubscraper.egg-info/dependency_links.txt
epubscraper.egg-info/requires.txt
epubscraper.egg-info/top_level.txt