Metadata-Version: 1.0
Name: epubscraper
Version: 3.2.3
Summary: Post generator for eboipotro.github.io
Home-page: https://eboipotro.github.io/
Author: Utsob Roy
Author-email: uroybd@gmail.com
License: UNKNOWN
Platform: UNKNOWN
